06_io_controler/cipher_core.sv
import cipher_pkg::*;

module cipher_core (
    input  logic                   clk_i,           // Rising edge active clk.
    input  logic                   rst_ni,          // Active low reset.
    input  logic [KEY_LENGTH-1:0]  key_i,           // Encryption key.
    input  logic [DATA_LENGTH-1:0] nonce_i,         // Nonce.
    input  logic [LENGTH-1:0]      data_len_i,      // # of data blocks.
    input  logic [LENGTH-1:0]      ad_len_i,        // # of ad blocks.
    input  logic [DATA_LENGTH-1:0] indata_i,        // Plaintext and AD.
    input  logic                   indata_valid_i,  // Master valid.
    output logic                   indata_ready_o,  // Slave ready.
    output logic [DATA_LENGTH-1:0] outdata_o,       // Ciphertext.
    output logic                   outdata_valid_o, // Slave valid.
    input  logic                   outdata_ready_i, // Master ready.
    output logic [DATA_LENGTH-1:0] tag_o,           // Tag.
    input  logic                   start_i,         // Start signal.
    output logic                   busy_o,          // Cipher busy.
    output logic                   finish_o         // Cipher finish.
);

    
    // ...

    // = blocking assignment
    // <= non-blocking assignment

    state_t curr_state, next_state;

    key_t key;
    logic [LENGTH-1:0] counter_init;
    logic [LENGTH-1:0] counter_rd_ad, counter_rd_ad_max;

    // state logic

    always_ff @(posedge clk_i) begin : currStateReg
        if (rst_ni == 0) begin
            curr_state <= idle;
        end 
        else begin
            curr_state <= next_state;
        end
    end : currStateReg

    always_comb begin : nextStateLogic
        next_state = curr_state; // default is to stay in current state
        case (curr_state)
            idle : begin
                if (start_i == 1) begin
                    next_state = init;
                end
            end
            init : begin
                if (counter_init == 16'h3) begin
                    next_state = read_ad;
                end
            end
            read_ad : begin
                if (indata_valid_i) begin
                    next_state = read_ad_check;
                end
            end
            read_ad_check : begin
                if (counter_rd_ad==counter_rd_ad_max) begin
                    next_state = read_data;
                end
                else begin
                    next_state = read_ad;
                end
            end
            read_data : begin
                next_state = compute;
            end
            compute : begin
                next_state = write_data;
            end
            write_data : begin
                next_state = write_tag;
            end
            write_tag : begin
                next_state = finish;
            end
            finish : begin
                next_state = idle;
            end
            default : begin
                next_state = idle;
            end
        endcase
    end : nextStateLogic

    // data logic

    always_ff @(posedge clk_i) begin : keyReg
        if (rst_ni == 0) begin
            key <= 0;
        end 
        else begin
            key <= key_i;
        end
    end : keyReg

    always_ff @(posedge clk_i) begin : counterDelayInitReg
        if (rst_ni == 0) begin
            counter_init <= 0;
        end 
        else begin
            if (curr_state == init) begin
                counter_init <= counter_init + 1;
            end
        end
    end : counterDelayInitReg

    always_ff @(posedge clk_i) begin : counterRdAdMaxReg
        if (rst_ni == 0) begin
            counter_rd_ad_max <= 0;
        end 
        else begin
            if (curr_state == init) begin
                counter_rd_ad_max <= ad_len_i;
            end
        end
    end : counterRdAdMaxReg

    always_ff @(posedge clk_i) begin : counterRdAdReg
        if (rst_ni == 0) begin
            counter_rd_ad_max <= 0;
        end 
        else begin
            if (curr_state == init) begin
                counter_rd_ad <= 0;
            end
            else if (curr_state == read_ad && indata_ready_o && indata_valid_i) begin
                counter_rd_ad <= counter_rd_ad + 1;
            end
        end
    end : counterRdAdReg

    // output logic

    // TODO Your implementation!

    assign indata_ready_o = (curr_state == read_ad || curr_state == read_data);
    assign outdata_o = {DATA_LENGTH{1'b0}};
    assign outdata_valid_o = 1'b0;
    assign tag_o = {DATA_LENGTH{1'b0}};
    assign busy_o = (curr_state != idle && curr_state != finish);
    assign finish_o = (curr_state == finish);


endmodule : cipher_core

06_io_controler/cipher_core_tb.sv

import cipher_pkg::*;

module cipher_core_tb;

    logic                   clk_i;           // Rising edge active clk.
    logic                   rst_ni;          // Active low reset.
    logic [KEY_LENGTH-1:0]  key_i;           // Encryption key.
    logic [DATA_LENGTH-1:0] nonce_i;         // Nonce.
    logic [LENGTH-1:0]      data_len_i;      // # of data blocks.
    logic [LENGTH-1:0]      ad_len_i;        // # of ad blocks.
    logic [DATA_LENGTH-1:0] indata_i;        // Plaintext and AD.
    logic                   indata_valid_i;  // Master valid.
    logic                   indata_ready_o;  // Slave ready.
    logic [DATA_LENGTH-1:0] outdata_o;       // Ciphertext.
    logic                   outdata_valid_o; // Slave valid.
    logic                   outdata_ready_i; // Master ready.
    logic [DATA_LENGTH-1:0] tag_o;           // Tag.
    logic                   start_i;         // Start signal.
    logic                   busy_o;          // Cipher busy. 
    logic                   finish_o;        // Cipher finish.

    // Instantiate cipher_core module
    cipher_core uut (
        .clk_i              (clk_i),           // Rising edge active clk.
        .rst_ni             (rst_ni),          // Active low reset.
        .key_i              (key_i),           // Encryption key.
        .nonce_i            (nonce_i),         // Nonce.
        .data_len_i         (data_len_i),      // # of data blocks.
        .ad_len_i           (ad_len_i),        // # of ad blocks.
        .indata_i           (indata_i),        // Plaintext and AD.
        .indata_valid_i     (indata_valid_i),  // Master valid.
        .indata_ready_o     (indata_ready_o),  // Slave ready.
        .outdata_o          (outdata_o),       // Ciphertext.
        .outdata_valid_o    (outdata_valid_o), // Slave valid.
        .outdata_ready_i    (outdata_ready_i), // Master ready.
        .tag_o              (tag_o),           // Tag.
        .start_i            (start_i),         // Start signal.
        .busy_o             (busy_o),          // Cipher busy. 
        .finish_o           (finish_o)         // Cipher finish.
    );

    // Clock generation
    initial forever #5 clk_i = ~clk_i;

    // Dumpfile 
    initial begin
        $dumpfile("cipher_core.vcd");
        $dumpvars(0, cipher_core_tb);
    end

    // Stimulus generation
    initial begin

        $display("\n=======================================");
        $display("> Start I/O control test");
        $display("=======================================\n");

        // Initialize inputs
        clk_i = 0;              // Rising edge active clk.
        rst_ni = 0;             // Active low reset.
        key_i = 0;              // Encryption key.
        nonce_i = 0;            // Nonce.
        data_len_i = 0;         // # of data blocks.
        ad_len_i = 0;           // # of ad blocks.
        indata_i = 0;           // Plaintext and AD.
        indata_valid_i = 0;     // Master valid.
        outdata_ready_i = 0;    // Master ready.
        start_i = 0;            // Start signal.

        #20;
        $display("> Set reset signal");
        rst_ni = 1;

        // #50;
        // $display("> Reset reset signal");
        // rst_ni = 1;

        #10;
        $display("> Set start signal");
        key_i = 128'h0123_4567_89ab_cdef_0123_4567_89ab_cdef;
        nonce_i = 128'hfedc_ba98_7654_3210_fedc_ba98_7654_3210;
        data_len_i = 2;
        ad_len_i = 2;
        indata_i = 0;
        indata_valid_i = 0;
        outdata_ready_i = 0;
        start_i = 1;

        #10;
        $display("> Reset start signal");
        start_i = 0;

        #10;
        $display("< Wait for  indata_ready_o signal");
        #100;
        while(indata_ready_o != 1) begin
            #10;
        end
        $display("> Set for  indata_valid_i signal");
        indata_valid_i = 1;
        indata_i = 128'had00_ad00_ad00_ad00_ad00_ad00_ad00_ad00;

        #10;
        $display("> Reset for indata_valid_i signal");
        indata_valid_i = 0;
        indata_i = 128'h0;

        #20;
        #5;
        $display("< Wait for indata_ready_o signal");
        while(indata_ready_o != 1);
        $display("> Set for indata_valid_i signal");
        indata_valid_i = 1;
        indata_i = 128'had01_ad01_ad01_ad01_ad01_ad01_ad01_ad01;

        #10;
        $display("> Reset for indata_valid_i signal");
        indata_valid_i = 0;
        indata_i = 128'h0;

        // TODO @students implement handling PT, CT, and TAG

        #10;
        $display("< Wait for finish signal");
        @(posedge finish_o)
        $display("> Received finish signal");

        $display("\n=======================================");
        $display("> Finish I/O control test");
        $display("=======================================\n");

        // Finish simulation
        #100;
        $finish;

    end

endmodule : cipher_core_tb

06_io_controler/cipher_core.vcd
$date
	Wed Mar 20 11:31:35 2024
$end
$version
	Icarus Verilog
$end
$timescale
	1s
$end
$scope module cipher_core_tb $end
$var wire 128 ! outdata_o [127:0] $end
$var wire 1 " outdata_valid_o $end
$var wire 128 # tag_o [127:0] $end
$var wire 1 $ indata_ready_o $end
$var wire 1 % finish_o $end
$var wire 1 & busy_o $end
$var reg 32 ' ad_len_i [31:0] $end
$var reg 1 ( clk_i $end
$var reg 32 ) data_len_i [31:0] $end
$var reg 128 * indata_i [127:0] $end
$var reg 1 + indata_valid_i $end
$var reg 128 , key_i [127:0] $end
$var reg 128 - nonce_i [127:0] $end
$var reg 1 . outdata_ready_i $end
$var reg 1 / rst_ni $end
$var reg 1 0 start_i $end
$scope module uut $end
$var wire 32 1 ad_len_i [31:0] $end
$var wire 1 & busy_o $end
$var wire 1 ( clk_i $end
$var wire 32 2 data_len_i [31:0] $end
$var wire 128 3 indata_i [127:0] $end
$var wire 1 $ indata_ready_o $end
$var wire 1 + indata_valid_i $end
$var wire 128 4 key_i [127:0] $end
$var wire 128 5 nonce_i [127:0] $end
$var wire 128 6 outdata_o [127:0] $end
$var wire 1 . outdata_ready_i $end
$var wire 1 " outdata_valid_o $end
$var wire 1 / rst_ni $end
$var wire 1 0 start_i $end
$var wire 128 7 tag_o [127:0] $end
$var wire 1 % finish_o $end
$var reg 32 8 counter_init [31:0] $end
$var reg 32 9 counter_rd_ad [31:0] $end
$var reg 32 : counter_rd_ad_max [31:0] $end
$var reg 128 ; key [127:0] $end
$var integer 32 < curr_state [31:0] $end
$var integer 32 = next_state [31:0] $end
$scope begin counterDelayInitReg $end
$upscope $end
$scope begin counterRdAdMaxReg $end
$upscope $end
$scope begin counterRdAdReg $end
$upscope $end
$scope begin currStateReg $end
$upscope $end
$scope begin keyReg $end
$upscope $end
$scope begin nextStateLogic $end
$upscope $end
$upscope $end
$upscope $end
$enddefinitions $end
#0
$dumpvars
b0 =
b0 <
bx ;
bx :
bx 9
bx 8
b0 7
b0 6
b0 5
b0 4
b0 3
b0 2
b0 1
00
0/
0.
b0 -
b0 ,
0+
b0 *
b0 )
0(
b0 '
0&
0%
0$
b0 #
0"
b0 !
$end
#5
b0 :
b0 8
b0 ;
1(
#10
0(
#15
1(
#20
0(
1/
#25
1(
#30
b1 =
0(
10
b10 '
b10 1
b10 )
b10 2
b11111110110111001011101010011000011101100101010000110010000100001111111011011100101110101001100001110110010101000011001000010000 -
b11111110110111001011101010011000011101100101010000110010000100001111111011011100101110101001100001110110010101000011001000010000 5
b1001000110100010101100111100010011010101111001101111011110000000100100011010001010110011110001001101010111100110111101111 ,
b1001000110100010101100111100010011010101111001101111011110000000100100011010001010110011110001001101010111100110111101111 4
#35
1&
b1001000110100010101100111100010011010101111001101111011110000000100100011010001010110011110001001101010111100110111101111 ;
b1 <
1(
#40
0(
00
#45
b0 9
b10 :
b1 8
1(
#50
0(
#55
b10 8
1(
#60
0(
#65
b10 =
b11 8
1(
#70
0(
#75
1$
b100 8
b10 <
1(
#80
0(
#85
1(
#90
0(
#95
1(
#100
0(
#105
1(
#110
0(
#115
1(
#120
0(
#125
1(
#130
0(
#135
1(
#140
0(
#145
1(
#150
b11 =
0(
b10101101000000001010110100000000101011010000000010101101000000001010110100000000101011010000000010101101000000001010110100000000 *
b10101101000000001010110100000000101011010000000010101101000000001010110100000000101011010000000010101101000000001010110100000000 3
1+
#155
b10 =
0$
b1 9
b11 <
1(
#160
b10 =
0(
b0 *
b0 3
0+
#165
1$
b10 <
1(
#170
0(
#175
1(
#180
0(
#185
0$
b10 9
b11 <
b100 =
1(
b10101101000000011010110100000001101011010000000110101101000000011010110100000001101011010000000110101101000000011010110100000001 *
b10101101000000011010110100000001101011010000000110101101000000011010110100000001101011010000000110101101000000011010110100000001 3
1+
#190
0(
#195
1$
b100 <
b101 =
1(
b0 *
b0 3
0+
#200
0(
#205
b110 =
0$
b101 <
1(
#210
0(
#215
b111 =
b110 <
1(
#220
0(
#225
b1000 =
b111 <
1(
#230
0(
#235
b0 =
0&
1%
b1000 <
1(
#240
0(
#245
0%
b0 <
1(
